{"inkVersion":20,"root":[[{"->":"Main"},["done",{"#f":5,"#n":"g-0"}],null],"done",{"Main":["^The spear! it's up there! ",{"#":"speaker:Rock Boy"},{"#":"layout:right"},{"#":"portrait:None"},"\n","end",{"#f":1}],"SpearGrabbed":["^Thank the crystals, it doesn't look like it's damaged... ",{"#":"speaker:Rock Boy"},{"#":"layout:right"},{"#":"portrait:None"},"\n","^Though I've never seen these small compartments, looks like something slid off the sides though.","\n","^Still! Got to keep moving forward. That... gross orange slime looks like it's too sticky to climb onto. But maybe the spear could stick to it!","\n","end",{"#f":1}],"CeilingWallStick":["^The green slime doesn't cover that whole wall, I can't move on! ",{"#":"speaker:Rock Boy"},{"#":"layout:right"},{"#":"portrait:None"},"\n","^Wait... these compartments... EUGH! SLIME??","\n","^But... they give me an idea. A crazy one. But it might work. Let's see what happens if I throw it up to that orange slime above me.","\n","end",{"#f":1}],"#f":1}],"listDefs":{}}